geometria/__init__.py
geometria/retangulo.py
geometria/triangulo.py
tests/__init__.py
tests/test_retangulo.py
tests/test_triangulo.py
geometria-0.5.dist-info/METADATA
geometria-0.5.dist-info/WHEEL
geometria-0.5.dist-info/top_level.txt
geometria-0.5.dist-info/RECORD
