Metadata-Version: 2.4
Name: geometria
Version: 0.5
Summary: Biblioteca para formulas de geometria
Author: Mayumi Shingaki
Classifier: Programming Language :: Python :: 3
Classifier: License :: OSI Approved :: MIT License
Classifier: Operating System :: OS Independent
Requires-Python: >=3.8
Dynamic: author
Dynamic: classifier
Dynamic: description
Dynamic: description-content-type
Dynamic: requires-python
Dynamic: summary
